{
  "/_app": "pages/_app.js",
  "/_error": "pages/_error.js",
  "/_document": "pages/_document.js",
  "/404": "pages/404.html",
  "/about": "pages/about.html",
  "/account/login": "pages/account/login.html",
  "/account/register": "pages/account/register.html",
  "/cart": "pages/cart.html",
  "/checkout": "pages/checkout.html",
  "/compare": "pages/compare.html",
  "/contact": "pages/contact.html",
  "/faq": "pages/faq.html",
  "/home/eight": "pages/home/eight.html",
  "/home/eighteen": "pages/home/eighteen.html",
  "/home/eleven": "pages/home/eleven.html",
  "/home/fifteen": "pages/home/fifteen.html",
  "/home/five": "pages/home/five.html",
  "/home/four": "pages/home/four.html",
  "/home/fourteen": "pages/home/fourteen.html",
  "/home/nine": "pages/home/nine.html",
  "/home/nineteen": "pages/home/nineteen.html",
  "/home/seventeen": "pages/home/seventeen.html",
  "/home/six": "pages/home/six.html",
  "/home/seven": "pages/home/seven.html",
  "/home/sixteen": "pages/home/sixteen.html",
  "/home/ten": "pages/home/ten.html",
  "/home/three": "pages/home/three.html",
  "/home/twelve": "pages/home/twelve.html",
  "/home/thirteen": "pages/home/thirteen.html",
  "/home/twenty": "pages/home/twenty.html",
  "/home/two": "pages/home/two.html",
  "/portfolio": "pages/portfolio.html",
  "/search": "pages/search.html",
  "/shop/full-width": "pages/shop/full-width.html",
  "/shop": "pages/shop.html",
  "/shop/left-sidebar": "pages/shop/left-sidebar.html",
  "/shop/right-sidebar": "pages/shop/right-sidebar.html",
  "/skin/books-shop-2": "pages/skin/books-shop-2.html",
  "/skin/books-shop": "pages/skin/books-shop.html",
  "/skin/cake-shop": "pages/skin/cake-shop.html",
  "/skin/care-shop": "pages/skin/care-shop.html",
  "/skin/clothes-shop": "pages/skin/clothes-shop.html",
  "/skin/comic-books-shop": "pages/skin/comic-books-shop.html",
  "/skin/cosmetics-shop": "pages/skin/cosmetics-shop.html",
  "/skin/echo-food-shop": "pages/skin/echo-food-shop.html",
  "/skin/electronics-shop": "pages/skin/electronics-shop.html",
  "/skin/flower-shop": "pages/skin/flower-shop.html",
  "/skin/food-shop": "pages/skin/food-shop.html",
  "/skin/furniture-shop": "pages/skin/furniture-shop.html",
  "/skin/glasses-shop": "pages/skin/glasses-shop.html",
  "/skin/gothic-clothing-shop": "pages/skin/gothic-clothing-shop.html",
  "/skin/handmade-shop": "pages/skin/handmade-shop.html",
  "/skin/jewelry-shop": "pages/skin/jewelry-shop.html",
  "/skin/kids-clothes-shop": "pages/skin/kids-clothes-shop.html",
  "/skin/kids-toys-shop": "pages/skin/kids-toys-shop.html",
  "/skin/oneproduct": "pages/skin/oneproduct.html",
  "/skin/phone-cases-shop": "pages/skin/phone-cases-shop.html",
  "/skin/phone-shop": "pages/skin/phone-shop.html",
  "/skin/snowboards-shop": "pages/skin/snowboards-shop.html",
  "/skin/tea-shop": "pages/skin/tea-shop.html",
  "/skin/wallets-shop": "pages/skin/wallets-shop.html",
  "/skin/watch-shop": "pages/skin/watch-shop.html",
  "/wishlist": "pages/wishlist.html",
  "/blog/full-width": "pages/blog/full-width.js",
  "/blog/[slug]": "pages/blog/[slug].js",
  "/blog": "pages/blog.js",
  "/product/[slug]": "pages/product/[slug].js",
  "/skin/baby-shop": "pages/skin/baby-shop.js",
  "/": "pages/index.js",
  "/skin/bicycle-shop": "pages/skin/bicycle-shop.js",
  "/skin/bike-shop": "pages/skin/bike-shop.js",
  "/product/category/[slug]": "pages/product/category/[slug].js",
  "/skin/cookware-shop": "pages/skin/cookware-shop.js",
  "/skin/car-shop": "pages/skin/car-shop.js",
  "/skin/lingerie-shop": "pages/skin/lingerie-shop.js",
  "/skin/medical-shop": "pages/skin/medical-shop.js",
  "/skin/t-shirt-shop": "pages/skin/t-shirt-shop.js",
  "/product/tag/[slug]": "pages/product/tag/[slug].js",
  "/skin/tools-shop": "pages/skin/tools-shop.js",
  "/skin/coffee-shop": "pages/skin/coffee-shop.js"
}